angrivhid97/__init__.py
angrivhid97-1.0.dist-info/LICENSE.txt
angrivhid97-1.0.dist-info/METADATA
angrivhid97-1.0.dist-info/WHEEL
angrivhid97-1.0.dist-info/top_level.txt
angrivhid97-1.0.dist-info/RECORD
