Metadata-Version: 2.1
Name: angrivhid97
Version: 1.0
Summary: A exercise example from EIP.
Home-page: UNKNOWN
Author: Lito Rivas Hidalgo
Author-email: angelrivashidalgo@gmail.com
License: GNU GPLv3
Keywords: angrivhid97 example EIP FPv4
Platform: UNKNOWN
Classifier: Development Status :: 3 - Alpha
Classifier: Intended Audience :: Developers
Classifier: Topic :: Utilities
Classifier: License :: OSI Approved :: GNU General Public License v3 (GPLv3)
Classifier: Programming Language :: Python :: 3
Classifier: Operating System :: OS Independent
License-File: LICENSE.txt
